pcatk/__init__.py
pcatk/convert.py
pcatk/exemplar.py
pcatk/feature.py
pcatk/measure.py
pcatk/util.py
pcatk/external/__init__.py
pcatk/external/ashlar_pyramid.py
pcatk/external/blockwise_view.py
pcatk-0.1.dist-info/LICENSE
pcatk-0.1.dist-info/METADATA
pcatk-0.1.dist-info/WHEEL
pcatk-0.1.dist-info/top_level.txt
pcatk-0.1.dist-info/RECORD
