Metadata-Version: 2.1
Name: pcatk
Version: 0.1
Summary: Pre-Cancer Atlas data analysis toolkit
Home-page: https://github.com/hungyiwu/pca_analysis_toolkit
Author: Hung-Yi Wu
Author-email: hungyi_wu@g.harvard.edu
License: UNKNOWN
Platform: UNKNOWN
Classifier: Programming Language :: Python :: 3
Classifier: License :: OSI Approved :: MIT License
Classifier: Operating System :: OS Independent
Requires-Dist: numpy
Requires-Dist: scikit-image
